unicode_tools/__init__.py
unicode_tools/database.py
unicode_tools/db.py
unicode_tools/normalize.py
unicode_tools/search.py
unicode_tools/uchr.py
uchr-0.3.0.dist-info/LICENSE
uchr-0.3.0.dist-info/METADATA
uchr-0.3.0.dist-info/WHEEL
uchr-0.3.0.dist-info/entry_points.txt
uchr-0.3.0.dist-info/RECORD
