Metadata-Version: 2.3
Name: uchr
Version: 0.3.0
Summary: Unicode character tools
License: MIT
Keywords: unicode,character,tools,cli
Author: Miki Yutani
Author-email: mkyutani@gmail.com
Requires-Python: >=3.8,<4.0
Classifier: Development Status :: 4 - Beta
Classifier: Environment :: Console
Classifier: Intended Audience :: Developers
Classifier: License :: OSI Approved :: MIT License
Classifier: Operating System :: OS Independent
Classifier: Programming Language :: Python :: 3
Classifier: Programming Language :: Python :: 3.8
Classifier: Programming Language :: Python :: 3.9
Classifier: Programming Language :: Python :: 3.10
Classifier: Programming Language :: Python :: 3.11
Classifier: Programming Language :: Python :: 3.12
Classifier: Programming Language :: Python :: 3.13
Classifier: Topic :: Software Development :: Libraries :: Python Modules
Classifier: Topic :: Text Processing :: General
Classifier: Topic :: Utilities
Requires-Dist: requests (>=2.25.0,<3.0.0)
Project-URL: Homepage, https://github.com/mkyutani/unicode-tools
Project-URL: Repository, https://github.com/mkyutani/unicode-tools
